hotetec_sdk/__init__.py
hotetec_sdk/config.py
hotetec_sdk/sdk.py
hotetec_sdk/entities/__init__.py
hotetec_sdk/entities/cancellation_restriction.py
hotetec_sdk/entities/hotel.py
hotetec_sdk/entities/room.py
hotetec_sdk/entities/room_service.py
jaalvarez2818_hotetec_sdk-0.2.15.dist-info/METADATA
jaalvarez2818_hotetec_sdk-0.2.15.dist-info/WHEEL
jaalvarez2818_hotetec_sdk-0.2.15.dist-info/top_level.txt
jaalvarez2818_hotetec_sdk-0.2.15.dist-info/RECORD
