Metadata-Version: 2.1
Name: jaalvarez2818-hotetec-sdk
Version: 0.2.15
Summary: SDK para la comunicación con el API de Hotetec para las reservas de hoteles.
Home-page: https://github.com/jaalvarez2818/hotetec-sdk
Author: José Angel Alvarez Abraira
Author-email: jaalvarez2818development@gmail.com
Classifier: Development Status :: 3 - Alpha
Classifier: Intended Audience :: Developers
Classifier: Programming Language :: Python :: 3
Classifier: Programming Language :: Python :: 3.7
Classifier: Programming Language :: Python :: 3.8
Classifier: Programming Language :: Python :: 3.9
Requires-Dist: requests
Requires-Dist: xmltodict
